lorax/README.md
lorax/__init__.py
lorax/__main__.py
lorax/data-new.txt
lorax/data.text
lorax/faiss_vector.py
lorax/graph.py
lorax/interface.py
lorax/langgraph_tskit.py
lorax/lorax_app.py
lorax/planner.py
lorax/test.ipynb
lorax/tools.py
lorax/utils.py
lorax/tskit-vector/index.faiss
lorax/tskit-vector/index.pkl
lorax/website/README.md
lorax/website/taxonium_component/.gitignore
lorax/website/taxonium_component/README.md
lorax/website/taxonium_component/index.html
lorax/website/taxonium_component/package.json
lorax/website/taxonium_component/postcss.config.cjs
lorax/website/taxonium_component/tailwind.config.js
lorax/website/taxonium_component/vercel.json
lorax/website/taxonium_component/vite.config.js
lorax/website/taxonium_component/yarn.lock
lorax/website/taxonium_component/.storybook/main.js
lorax/website/taxonium_component/.storybook/preview.js
lorax/website/taxonium_component/dist/android-chrome-144x144.png
lorax/website/taxonium_component/dist/apple-touch-icon.png
lorax/website/taxonium_component/dist/browserconfig.xml
lorax/website/taxonium_component/dist/favicon-16x16.png
lorax/website/taxonium_component/dist/favicon-32x32.png
lorax/website/taxonium_component/dist/favicon.ico
lorax/website/taxonium_component/dist/index.html
lorax/website/taxonium_component/dist/manifest.json
lorax/website/taxonium_component/dist/mstile-150x150.png
lorax/website/taxonium_component/dist/output.taxodium.pb
lorax/website/taxonium_component/dist/parsimony.proto
lorax/website/taxonium_component/dist/public-latest.all.masked.taxodium.pb.gz
lorax/website/taxonium_component/dist/robots.txt
lorax/website/taxonium_component/dist/safari-pinned-tab.svg
lorax/website/taxonium_component/dist/site.webmanifest
lorax/website/taxonium_component/dist/tfci-taxonium2.jsonl.gz
lorax/website/taxonium_component/dist/tfci.jsonl
lorax/website/taxonium_component/dist/assets/index-30810c83.js
lorax/website/taxonium_component/public/android-chrome-144x144.png
lorax_ai-0.1.0.dist-info/METADATA
lorax_ai-0.1.0.dist-info/WHEEL
lorax_ai-0.1.0.dist-info/entry_points.txt
lorax_ai-0.1.0.dist-info/top_level.txt
lorax_ai-0.1.0.dist-info/RECORD
